{
  "project_info": {
    "project_number": "803697812704",
    "firebase_url": "https://qfpay-1dedb.firebaseio.com",
    "project_id": "qfpay-1dedb",
    "storage_bucket": "qfpay-1dedb.appspot.com"
  },
  "client": [
    {
      "client_info": {
        "mobilesdk_app_id": "1:803697812704:android:fb75f6dd775e3c01",
        "android_client_info": {
          "package_name": "org.websocket.demo"
        }
      },
      "oauth_client": [
        {
          "client_id": "803697812704-cfbepgagh3o5hndi65vl22idrmujev9p.apps.googleusercontent.com",
          "client_type": 3
        }
      ],
      "api_key": [
        {
          "current_key": "AIzaSyBoeEcUSVhaUHccJpanI17p8YWsjnutyYg"
        }
      ],
      "services": {
        "analytics_service": {
          "status": 1
        },
        "appinvite_service": {
          "status": 1,
          "other_platform_oauth_client": []
        },
        "ads_service": {
          "status": 2
        }
      }
    }
  ],
  "configuration_version": "1"
}